friendlyloris/__init__.py
friendlyloris/friendlyloris.py
friendlyloris-1.0.1.dist-info/LICENSE
friendlyloris-1.0.1.dist-info/METADATA
friendlyloris-1.0.1.dist-info/WHEEL
friendlyloris-1.0.1.dist-info/top_level.txt
friendlyloris-1.0.1.dist-info/RECORD
